vsthost.cpython-313-darwin.so
sinesurge_vst-0.2.dist-info/METADATA
sinesurge_vst-0.2.dist-info/WHEEL
sinesurge_vst-0.2.dist-info/top_level.txt
sinesurge_vst-0.2.dist-info/RECORD
